juju_verify/__init__.py
juju_verify/exceptions.py
juju_verify/juju_verify.py
juju_verify/utils/__init__.py
juju_verify/utils/action.py
juju_verify/utils/unit.py
juju_verify/verifiers/__init__.py
juju_verify/verifiers/base.py
juju_verify/verifiers/ceph.py
juju_verify/verifiers/nova_compute.py
juju_verify/verifiers/result.py
juju_verify-0.2.1.dist-info/LICENSE.txt
juju_verify-0.2.1.dist-info/METADATA
juju_verify-0.2.1.dist-info/WHEEL
juju_verify-0.2.1.dist-info/entry_points.txt
juju_verify-0.2.1.dist-info/top_level.txt
juju_verify-0.2.1.dist-info/RECORD
